buf/__init__.py
buf/validate/__init__.py
buf/validate/expression_pb2.py
buf/validate/expression_pb2_grpc.py
buf/validate/validate_pb2.py
buf/validate/validate_pb2.pyi
buf/validate/validate_pb2_grpc.py
buf/validate/priv/__init__.py
buf/validate/priv/private_pb2.py
buf/validate/priv/private_pb2_grpc.py
inventory_grpc_clients_python_kessel_project-0.10.15.dist-info/licenses/LICENSE
kessel/__init__.py
kessel/inventory/__init__.py
kessel/inventory/v1/__init__.py
kessel/inventory/v1/health_pb2.py
kessel/inventory/v1/health_pb2_grpc.py
kessel/inventory/v1beta1/__init__.py
kessel/inventory/v1beta1/authz/__init__.py
kessel/inventory/v1beta1/authz/check_pb2.py
kessel/inventory/v1beta1/authz/check_pb2_grpc.py
kessel/inventory/v1beta1/authz/common_pb2.py
kessel/inventory/v1beta1/authz/common_pb2_grpc.py
kessel/inventory/v1beta1/relationships/__init__.py
kessel/inventory/v1beta1/relationships/k8spolicy_ispropagatedto_k8scluster_detail_pb2.py
kessel/inventory/v1beta1/relationships/k8spolicy_ispropagatedto_k8scluster_detail_pb2_grpc.py
kessel/inventory/v1beta1/relationships/k8spolicy_ispropagatedto_k8scluster_pb2.py
kessel/inventory/v1beta1/relationships/k8spolicy_ispropagatedto_k8scluster_pb2_grpc.py
kessel/inventory/v1beta1/relationships/k8spolicy_ispropagatedto_k8scluster_service_pb2.py
kessel/inventory/v1beta1/relationships/k8spolicy_ispropagatedto_k8scluster_service_pb2_grpc.py
kessel/inventory/v1beta1/relationships/metadata_pb2.py
kessel/inventory/v1beta1/relationships/metadata_pb2_grpc.py
kessel/inventory/v1beta1/relationships/reporter_data_pb2.py
kessel/inventory/v1beta1/relationships/reporter_data_pb2_grpc.py
kessel/inventory/v1beta1/resources/__init__.py
kessel/inventory/v1beta1/resources/k8s_cluster_detail_nodes_inner_pb2.py
kessel/inventory/v1beta1/resources/k8s_cluster_detail_nodes_inner_pb2_grpc.py
kessel/inventory/v1beta1/resources/k8s_cluster_detail_pb2.py
kessel/inventory/v1beta1/resources/k8s_cluster_detail_pb2_grpc.py
kessel/inventory/v1beta1/resources/k8s_cluster_pb2.py
kessel/inventory/v1beta1/resources/k8s_cluster_pb2_grpc.py
inventory_grpc_clients_python_kessel_project-0.10.15.dist-info/METADATA
inventory_grpc_clients_python_kessel_project-0.10.15.dist-info/WHEEL
inventory_grpc_clients_python_kessel_project-0.10.15.dist-info/top_level.txt
inventory_grpc_clients_python_kessel_project-0.10.15.dist-info/RECORD
