Metadata-Version: 2.4
Name: inventory-grpc-clients-python-kessel-project
Version: 0.10.15
Summary: This package contains grpc python clients based on kessel inventory-api.
Home-page: https://github.com/project-kessel/inventory-client-python
Author: Christopher Sams
Author-email: "Christopher Sams" <csams@redhat.com>
License: Apache-2.0
Classifier: License :: OSI Approved :: Apache Software License
Classifier: Programming Language :: Python
Classifier: Programming Language :: Python :: 3.9
Classifier: Operating System :: OS Independent
Requires-Python: >=3.8
License-File: LICENSE
Requires-Dist: grpcio>=1.73.0
Requires-Dist: protobuf>=6.30.0
Dynamic: license-file
